textpack/__init__.py
textpack/tp.py
textpack-0.0.7.dist-info/LICENSE
textpack-0.0.7.dist-info/METADATA
textpack-0.0.7.dist-info/WHEEL
textpack-0.0.7.dist-info/top_level.txt
textpack-0.0.7.dist-info/RECORD
