Metadata-Version: 2.1
Name: textpack
Version: 0.0.7
Summary: Quickly identify and group similar text strings in a large dataset
Home-page: https://github.com/lukewhyte/textpack
Author: Luke Whyte
Author-email: lukeawhyte@gmail.com
License: UNKNOWN
Platform: UNKNOWN
Classifier: Programming Language :: Python :: 3
Classifier: License :: OSI Approved :: MIT License
Classifier: Operating System :: OS Independent
Requires-Dist: pandas
Requires-Dist: sklearn
Requires-Dist: scipy
Requires-Dist: numpy
Requires-Dist: cython
Requires-Dist: sparse-dot-topn
